pydeepseek/__init__.py
pydeepseek/core.py
pydeepseek-1.0.1.dist-info/METADATA
pydeepseek-1.0.1.dist-info/WHEEL
pydeepseek-1.0.1.dist-info/top_level.txt
pydeepseek-1.0.1.dist-info/RECORD
