Metadata-Version: 2.4
Name: pydeepseek
Version: 1.0.1
Summary: Python wrapper for DeepSeek V3 model
Home-page: https://github.com/yourusername/deepseek-v3
Author: LongTime
Author-email: noreply@long-time.ru
Classifier: Programming Language :: Python :: 3
Classifier: License :: OSI Approved :: MIT License
Requires-Python: >=3.6
Requires-Dist: requests
Dynamic: author
Dynamic: author-email
Dynamic: classifier
Dynamic: description
Dynamic: description-content-type
Dynamic: home-page
Dynamic: requires-dist
Dynamic: requires-python
Dynamic: summary
